gx_mcp_server/__init__.py
gx_mcp_server/__main__.py
gx_mcp_server/basic_auth.py
gx_mcp_server/bearer_auth.py
gx_mcp_server/logging.py
gx_mcp_server/oauth_token.py
gx_mcp_server/origin_validator.py
gx_mcp_server/server.py
gx_mcp_server/connectors/__init__.py
gx_mcp_server/connectors/bigquery.py
gx_mcp_server/connectors/snowflake.py
gx_mcp_server/core/__init__.py
gx_mcp_server/core/context.py
gx_mcp_server/core/schema.py
gx_mcp_server/core/storage.py
gx_mcp_server/storage/__init__.py
gx_mcp_server/storage/sqlite_backend.py
gx_mcp_server/tools/__init__.py
gx_mcp_server/tools/datasets.py
gx_mcp_server/tools/expectations.py
gx_mcp_server/tools/health.py
gx_mcp_server/tools/validation.py
gx_mcp_server-2.0.3.dist-info/METADATA
gx_mcp_server-2.0.3.dist-info/WHEEL
gx_mcp_server-2.0.3.dist-info/entry_points.txt
gx_mcp_server-2.0.3.dist-info/licenses/LICENSE
gx_mcp_server-2.0.3.dist-info/RECORD
