Metadata-Version: 2.4
Name: gx-mcp-server
Version: 2.0.3
Summary: Expose Great Expectations data-quality checks via MCP
Project-URL: Homepage, https://github.com/dfront/gx-mcp-server
Project-URL: Repository, https://github.com/dfront/gx-mcp-server
Project-URL: Issues, https://github.com/dfront/gx-mcp-server/issues
Project-URL: Documentation, https://github.com/dfront/gx-mcp-server#readme
Author-email: David Front <dfront@gmail.com>
Maintainer-email: David Front <dfront@gmail.com>
License: MIT License
License-File: LICENSE
Keywords: data validation,great-expectations,mcp
Classifier: Development Status :: 3 - Alpha
Classifier: Intended Audience :: Developers
Classifier: Programming Language :: Python :: 3
Classifier: Programming Language :: Python :: 3.11
Classifier: Programming Language :: Python :: 3.12
Requires-Python: >=3.11
Requires-Dist: fastapi>=0.116.1
Requires-Dist: fastmcp>=2.10.0
Requires-Dist: great-expectations>=0.17
Requires-Dist: opentelemetry-exporter-otlp>=1
Requires-Dist: opentelemetry-instrumentation-fastapi>=0.46
Requires-Dist: opentelemetry-sdk>=1
Requires-Dist: pandas>=1.5
Requires-Dist: polars>=0.20
Requires-Dist: prometheus-fastapi-instrumentator>=7
Requires-Dist: pydantic>=1
Requires-Dist: requests>=2.28
Requires-Dist: scipy>=1.13
Requires-Dist: slowapi>=0.1.9
Provides-Extra: bigquery
Requires-Dist: google-cloud-bigquery; extra == 'bigquery'
Provides-Extra: dev
Requires-Dist: bump-my-version; extra == 'dev'
Requires-Dist: colorama; extra == 'dev'
Requires-Dist: fastapi; extra == 'dev'
Requires-Dist: mypy; extra == 'dev'
Requires-Dist: openai; extra == 'dev'
Requires-Dist: pandas-stubs; extra == 'dev'
Requires-Dist: pre-commit; extra == 'dev'
Requires-Dist: pytest; extra == 'dev'
Requires-Dist: pytest-asyncio; extra == 'dev'
Requires-Dist: python-dotenv; extra == 'dev'
Requires-Dist: ruff; extra == 'dev'
Requires-Dist: types-authlib; extra == 'dev'
Requires-Dist: types-requests; extra == 'dev'
Provides-Extra: snowflake
Requires-Dist: snowflake-connector-python; extra == 'snowflake'
